LICENSE
MANIFEST.in
README.md
make.sh
requirements.txt
setup.cfg
setup.py
Moustache_fusion.beta.egg-info/PKG-INFO
Moustache_fusion.beta.egg-info/SOURCES.txt
Moustache_fusion.beta.egg-info/dependency_links.txt
Moustache_fusion.beta.egg-info/entry_points.txt
Moustache_fusion.beta.egg-info/requires.txt
Moustache_fusion.beta.egg-info/top_level.txt
config/logging_config.json
moustache_fusion/__init__.py
moustache_fusion/datatransfer.py
moustache_fusion/exceptions.py
moustache_fusion/logger.py
moustache_fusion/skittlesproc.py
moustache_fusion/skittlespy.py
moustache_fusion/utilities.py
moustache_fusion/webservice.py
moustache_fusion/static/favicon.ico
moustache_fusion/static/moustache-swap.png
moustache_fusion/templates/index.html
tests/__init__.py
tests/conftest.py
tests/cases/__init__.py
tests/cases/utilities/__init__.py
tests/cases/utilities/test_generator.py
tests/cases/utilities/test_pdf.py
tests/cases/webservice/__init__.py
tests/cases/webservice/api_v1_pdf_swap/__init__.py
tests/cases/webservice/api_v1_pdf_swap/test_failure.py
tests/cases/webservice/api_v1_pdf_swap/test_success.py
tests/cases/webservice/www_v1/__init__.py
tests/cases/webservice/www_v1/test_index.py
tests/fixtures/inner_1_page/dylan_thomas_night.odt
tests/fixtures/inner_1_page/dylan_thomas_night.pdf
tests/fixtures/inner_1_page/dylan_thomas_wood.odt
tests/fixtures/inner_1_page/dylan_thomas_wood.pdf
tests/fixtures/inner_1_page/edgar_allan_poe_murders-pdf_a_1a.pdf
tests/fixtures/inner_1_page/edgar_allan_poe_murders-with_document_open_password.pdf
tests/fixtures/inner_1_page/edgar_allan_poe_murders-with_embedded_odt.pdf
tests/fixtures/inner_1_page/edgar_allan_poe_murders-with_permission_password.pdf
tests/fixtures/inner_1_page/edgar_allan_poe_murders.odt
tests/fixtures/inner_1_page/edgar_allan_poe_murders.pdf
tests/fixtures/inner_3_pages/lorem_ipsum-corrupted.pdf
tests/fixtures/inner_3_pages/lorem_ipsum-pdf_a_1a.pdf
tests/fixtures/inner_3_pages/lorem_ipsum-with_embedded_odt.pdf
tests/fixtures/inner_3_pages/lorem_ipsum.odt
tests/fixtures/inner_3_pages/lorem_ipsum.pdf
tests/fixtures/main10p_m3p_i3p_m1p_i1p_m2p/failure_with_non_unique_patterns.json
tests/fixtures/main10p_m3p_i3p_m1p_i1p_m2p/main-corrupted.pdf
tests/fixtures/main10p_m3p_i3p_m1p_i1p_m2p/main-pdf_a_1a.pdf
