Metadata-Version: 2.1
Name: Moustache-fusion.beta
Version: 0.0.2.post164219
Summary: Module post-Moustache pour fusion d'annexes PDF dans PDF principal
Home-page: https://gitlab.libriciel.fr/outils/skittlespy/
Author: Libriciel SCOP
Author-email: hackathon@libriciel.coop
License: CeCILL-2.1
Platform: UNKNOWN
Classifier: Development Status :: 4 - Beta
Classifier: Environment :: Web Environment
Classifier: Framework :: Flask
Classifier: License :: OSI Approved :: CEA CNRS Inria Logiciel Libre License, version 2.1 (CeCILL-2.1)
Classifier: Operating System :: POSIX :: Linux
Classifier: Programming Language :: Python :: 3 :: Only
Classifier: Programming Language :: Python :: 3.6
Requires-Python: >=3
Provides-Extra: dev
